aeterdum/__init__.py
aeterdum/client.py
aeterdum/crypto.py
aeterdum/resources/logs.py
aeterdum-1.0.2.dist-info/licenses/LICENSE
aeterdum-1.0.2.dist-info/METADATA
aeterdum-1.0.2.dist-info/WHEEL
aeterdum-1.0.2.dist-info/top_level.txt
aeterdum-1.0.2.dist-info/RECORD
