Metadata-Version: 2.4
Name: aeterdum
Version: 1.0.2
Summary: Official Python client for Aeterdum
Author-email: Aeterdum <contact@aeterdum.com>
License: MIT
Project-URL: Homepage, https://aeterdum.com
Project-URL: Source, https://github.com/aeterdum/
Keywords: aeterdum,audit-log,sdk,api
Classifier: Development Status :: 3 - Alpha
Classifier: Intended Audience :: Developers
Classifier: Programming Language :: Python :: 3
Requires-Python: >=3.8
License-File: LICENSE
Requires-Dist: httpx>=0.23.0
Dynamic: license-file
